logic/__init__.py
logic/proof.py
logic/proposition.py
logic/utils.py
py_logic-0.1.1.dist-info/METADATA
py_logic-0.1.1.dist-info/WHEEL
py_logic-0.1.1.dist-info/licenses/LICENSE
py_logic-0.1.1.dist-info/RECORD
