Metadata-Version: 2.1
Name: py-logic
Version: 0.1.1
Summary: Library to use and simulate propositional logic
Project-URL: Homepage, https://github.com/Vipul-Cariappa/logic
Project-URL: Bug Tracker, https://github.com/Vipul-Cariappa/logic/issues
Author-email: Vipul Cariappa <vipulcariappa@gmail.com>
License: MIT License
License-File: LICENSE
Classifier: License :: OSI Approved :: MIT License
Classifier: Operating System :: OS Independent
Classifier: Programming Language :: Python :: 3
Requires-Python: >=3.10
